twitter_variation/__init__.py
twitter_variation/variation_to_english_dict.pickle
twitter_variation-1.0.2.dist-info/METADATA
twitter_variation-1.0.2.dist-info/RECORD
twitter_variation-1.0.2.dist-info/WHEEL
twitter_variation-1.0.2.dist-info/top_level.txt
